autocomplete_chained/__init__.py
autocomplete_chained/admin.py
autocomplete_chained/apps.py
autocomplete_chained/models.py
autocomplete_chained/urls.py
autocomplete_chained/views.py
autocomplete_chained/widgets.py
autocomplete_chained/static/dist/autocomplete_chained.js
django_chained_autocomplete-0.0.8.dist-info/DESCRIPTION.rst
django_chained_autocomplete-0.0.8.dist-info/METADATA
django_chained_autocomplete-0.0.8.dist-info/RECORD
django_chained_autocomplete-0.0.8.dist-info/WHEEL
django_chained_autocomplete-0.0.8.dist-info/metadata.json
django_chained_autocomplete-0.0.8.dist-info/top_level.txt
