Metadata-Version: 2.0
Name: django-chained-autocomplete
Version: 0.0.8
Summary: Chain autocomplete dropdowns in django admin.
Home-page: http://github.com/alpha1d3d/django-chained-autocomplete
Author: Jonathan Loo
Author-email: alpha1d3d@hotmail.com
License: MIT
Keywords: django autocomplete chained filtered
Platform: UNKNOWN
Classifier: Development Status :: 3 - Alpha
Classifier: License :: OSI Approved :: MIT License
Classifier: Programming Language :: Python :: 3.6
Classifier: Framework :: Django :: 2.1
Requires-Python: >=3.6
Requires-Dist: django
